sensu_plugins_aws_subnet/__init__.py
sensu_plugins_aws_subnet/__main__.py
sensu_plugins_aws_subnet-0.1.4.data/scripts/sensu-check-aws-subnet
sensu_plugins_aws_subnet-0.1.4.dist-info/LICENSE
sensu_plugins_aws_subnet-0.1.4.dist-info/METADATA
sensu_plugins_aws_subnet-0.1.4.dist-info/WHEEL
sensu_plugins_aws_subnet-0.1.4.dist-info/top_level.txt
sensu_plugins_aws_subnet-0.1.4.dist-info/RECORD
