Metadata-Version: 2.1
Name: sensu-plugins-aws-subnet
Version: 0.1.4
Summary: A extention from Python sensu plugins framework to check aws subnet available IPs
Home-page: https://github.com/supernova106/sensu_plugins_aws_subnet
Author: Binh Nguyen
Author-email: binhnguyen@ebates.com
License: BSD
Platform: UNKNOWN
Requires-Python: >=3
Requires-Dist: boto3
Requires-Dist: ipaddress
Requires-Dist: sensu-plugin
